README.md
setup.cfg
setup.py
gsmsapi/__init__.py
gsmsapi/cmtelecom_api.py
gsmsapi/sipgate_api.py
gsmsapi/smstrade_api.py
gsmsapi.egg-info/PKG-INFO
gsmsapi.egg-info/SOURCES.txt
gsmsapi.egg-info/dependency_links.txt
gsmsapi.egg-info/requires.txt
gsmsapi.egg-info/top_level.txt